gfeatpy/__init__.py
gfeatpy/_core.cpython-312-x86_64-linux-musl.so
gfeatpy/gravity.py
gfeatpy/main.cpp
gfeatpy/observation.py
gfeatpy/plotting.py
gfeatpy/py_gravity.hpp
gfeatpy/py_observation.hpp
gfeatpy/py_utils.hpp
gfeatpy/utils.py
gfeatpy.libs/libgcc_s-0cd532bd.so.1
gfeatpy.libs/libgomp-8949ffbe.so.1.0.0
gfeatpy.libs/libstdc++-5d72f927.so.6.0.33
gfeatpy-0.1.1.dist-info/METADATA
gfeatpy-0.1.1.dist-info/WHEEL
gfeatpy-0.1.1.dist-info/RECORD
gfeatpy-0.1.1.dist-info/licenses/LICENSE
gfeatpy-0.1.1.dist-info/sboms/auditwheel.cdx.json
