Metadata-Version: 2.4
Name: gfeatpy
Version: 0.1.1
Summary: A Python wrapper for a C++ gravity field error analysis toolkit. 
Author-Email: Gabriel Valles <gvallesv@outlook.es>
License-Expression: GPL-3.0-or-later
License-File: LICENSE
Requires-Python: >=3.11
Requires-Dist: numpy>=1.23
Requires-Dist: matplotlib>=3.5
Requires-Dist: cartopy>=0.21.1
